{
	"root_intelligence": {
		"title": "kubejs.puffskill.def.root_intelligence.title",
		"description": "kubejs.puffskill.def.root_intelligence.desc",
		"extra_description": "kubejs.puffskill.exdesc.decode_ability",
		"frame": {
			"type": "advancement",
			"data": {
				"frame": "challenge"
			}
		},
		"icon": {
			"type": "effect",
			"data": {
				"effect": "health_boost"
			}
		},
		"rewards": [
			{
				"type": "puffish_skills:attribute",
				"data": {
					"attribute": "kubejs:decode_ability",
					"value": 1,
					"operation": "addition"
				}
			}
		]
	},
	"cold_damage_add_05": {
		"title": "kubejs.puffskill.def.cold_damage_add_05.title",
		"description": "kubejs.puffskill.def.cold_damage_add_05.desc",
		"extra_description": "kubejs.puffskill.exdesc.cold_damage",
		"frame": {
			"type": "advancement",
			"data": {
				"frame": "task"
			}
		},
		"icon": {
			"type": "effect",
			"data": {
				"effect": "health_boost"
			}
		},
		"rewards": [
			{
				"type": "puffish_skills:attribute",
				"data": {
					"attribute": "attributeslib:cold_damage",
					"value": 0.5,
					"operation": "addition"
				}
			}
		]
	},
	"cold_damage_add_1": {
		"title": "kubejs.puffskill.def.cold_damage_add_1.title",
		"description": "kubejs.puffskill.def.cold_damage_add_1.desc",
		"extra_description": "kubejs.puffskill.exdesc.cold_damage",
		"frame": {
			"type": "advancement",
			"data": {
				"frame": "goal"
			}
		},
		"icon": {
			"type": "effect",
			"data": {
				"effect": "health_boost"
			}
		},
		"rewards": [
			{
				"type": "puffish_skills:attribute",
				"data": {
					"attribute": "attributeslib:cold_damage",
					"value": 1,
					"operation": "addition"
				}
			}
		]
	},
	"cold_damage_add_2": {
		"title": "kubejs.puffskill.def.cold_damage_add_2.title",
		"description": "kubejs.puffskill.def.cold_damage_add_2.desc",
		"extra_description": "kubejs.puffskill.exdesc.cold_damage",
		"frame": {
			"type": "advancement",
			"data": {
				"frame": "challenge"
			}
		},
		"icon": {
			"type": "effect",
			"data": {
				"effect": "health_boost"
			}
		},
		"rewards": [
			{
				"type": "puffish_skills:attribute",
				"data": {
					"attribute": "attributeslib:cold_damage",
					"value": 2,
					"operation": "addition"
				}
			}
		]
	},
	"cold_damage_multiply_base_05": {
		"title": "kubejs.puffskill.def.cold_damage_multiply_base_05.title",
		"description": "kubejs.puffskill.def.cold_damage_multiply_base_05.desc",
		"extra_description": "kubejs.puffskill.exdesc.cold_damage_multiply_base_05",
		"frame": {
			"type": "advancement",
			"data": {
				"frame": "challenge"
			}
		},
		"icon": {
			"type": "effect",
			"data": {
				"effect": "health_boost"
			}
		},
		"rewards": [
			{
				"type": "puffish_skills:attribute",
				"data": {
					"attribute": "attributeslib:cold_damage",
					"value": 0.5,
					"operation": "multiply_base"
				}
			},
			{
				"type": "puffish_skills:attribute",
				"data": {
					"attribute": "attributeslib:fire_damage",
					"value": -1,
					"operation": "multiply_base"
				}
			}
		]
	},
	"fire_damage_add_05": {
		"title": "kubejs.puffskill.def.fire_damage_add_05.title",
		"description": "kubejs.puffskill.def.fire_damage_add_05.desc",
		"extra_description": "kubejs.puffskill.exdesc.fire_damage",
		"frame": {
			"type": "advancement",
			"data": {
				"frame": "task"
			}
		},
		"icon": {
			"type": "effect",
			"data": {
				"effect": "health_boost"
			}
		},
		"rewards": [
			{
				"type": "puffish_skills:attribute",
				"data": {
					"attribute": "attributeslib:fire_damage",
					"value": 0.5,
					"operation": "addition"
				}
			}
		]
	},
	"fire_damage_add_1": {
		"title": "kubejs.puffskill.def.fire_damage_add_1.title",
		"description": "kubejs.puffskill.def.fire_damage_add_1.desc",
		"extra_description": "kubejs.puffskill.exdesc.fire_damage",
		"frame": {
			"type": "advancement",
			"data": {
				"frame": "goal"
			}
		},
		"icon": {
			"type": "effect",
			"data": {
				"effect": "health_boost"
			}
		},
		"rewards": [
			{
				"type": "puffish_skills:attribute",
				"data": {
					"attribute": "attributeslib:fire_damage",
					"value": 1,
					"operation": "addition"
				}
			}
		]
	},
	"fire_damage_add_2": {
		"title": "kubejs.puffskill.def.fire_damage_add_2.title",
		"description": "kubejs.puffskill.def.fire_damage_add_2.desc",
		"extra_description": "kubejs.puffskill.exdesc.fire_damage",
		"frame": {
			"type": "advancement",
			"data": {
				"frame": "challenge"
			}
		},
		"icon": {
			"type": "effect",
			"data": {
				"effect": "health_boost"
			}
		},
		"rewards": [
			{
				"type": "puffish_skills:attribute",
				"data": {
					"attribute": "attributeslib:fire_damage",
					"value": 2,
					"operation": "addition"
				}
			}
		]
	},
	"fire_damage_multiply_base_05": {
		"title": "kubejs.puffskill.def.fire_damage_multiply_base_05.title",
		"description": "kubejs.puffskill.def.fire_damage_multiply_base_05.desc",
		"extra_description": "kubejs.puffskill.exdesc.fire_damage_multiply_base_05",
		"frame": {
			"type": "advancement",
			"data": {
				"frame": "challenge"
			}
		},
		"icon": {
			"type": "effect",
			"data": {
				"effect": "health_boost"
			}
		},
		"rewards": [
			{
				"type": "puffish_skills:attribute",
				"data": {
					"attribute": "attributeslib:fire_damage",
					"value": 0.5,
					"operation": "multiply_base"
				}
			},
			{
				"type": "puffish_skills:attribute",
				"data": {
					"attribute": "attributeslib:cold_damage",
					"value": -1,
					"operation": "multiply_base"
				}
			}
		]
	},
	"luck_add_05": {
		"title": "kubejs.puffskill.def.luck_add_05.title",
		"description": "kubejs.puffskill.def.luck_add_05.desc",
		"extra_description": "kubejs.puffskill.exdesc.luck",
		"frame": {
			"type": "advancement",
			"data": {
				"frame": "task"
			}
		},
		"icon": {
			"type": "effect",
			"data": {
				"effect": "health_boost"
			}
		},
		"rewards": [
			{
				"type": "puffish_skills:attribute",
				"data": {
					"attribute": "minecraft:generic.luck",
					"value": 0.5,
					"operation": "addition"
				}
			}
		]
	},
	"luck_add_1": {
		"title": "kubejs.puffskill.def.luck_add_1.title",
		"description": "kubejs.puffskill.def.luck_add_1.desc",
		"extra_description": "kubejs.puffskill.exdesc.luck",
		"frame": {
			"type": "advancement",
			"data": {
				"frame": "goal"
			}
		},
		"icon": {
			"type": "effect",
			"data": {
				"effect": "health_boost"
			}
		},
		"rewards": [
			{
				"type": "puffish_skills:attribute",
				"data": {
					"attribute": "minecraft:generic.luck",
					"value": 1,
					"operation": "addition"
				}
			}
		]
	},
	"fortune_add_05": {
		"title": "kubejs.puffskill.def.fortune_add_05.title",
		"description": "kubejs.puffskill.def.fortune_add_05.desc",
		"extra_description": "kubejs.puffskill.exdesc.fortune",
		"frame": {
			"type": "advancement",
			"data": {
				"frame": "challenge"
			}
		},
		"icon": {
			"type": "effect",
			"data": {
				"effect": "health_boost"
			}
		},
		"rewards": [
			{
				"type": "puffish_skills:attribute",
				"data": {
					"attribute": "puffish_attributes:player.fortune",
					"value": 0.5,
					"operation": "addition"
				}
			}
		]
	},
	"fortune_add_1": {
		"title": "kubejs.puffskill.def.fortune_add_1.title",
		"description": "kubejs.puffskill.def.fortune_add_1.desc",
		"extra_description": "kubejs.puffskill.exdesc.fortune",
		"frame": {
			"type": "advancement",
			"data": {
				"frame": "challenge"
			}
		},
		"icon": {
			"type": "effect",
			"data": {
				"effect": "health_boost"
			}
		},
		"rewards": [
			{
				"type": "puffish_skills:attribute",
				"data": {
					"attribute": "puffish_attributes:player.fortune",
					"value": 1,
					"operation": "addition"
				}
			}
		]
	},
	"treasure_distance_reduce_16": {
		"title": "kubejs.puffskill.def.treasure_distance_reduce_16.title",
		"description": "kubejs.puffskill.def.treasure_distance_reduce_16.desc",
		"extra_description": "kubejs.puffskill.exdesc.treasure_distance",
		"frame": {
			"type": "advancement",
			"data": {
				"frame": "task"
			}
		},
		"icon": {
			"type": "effect",
			"data": {
				"effect": "health_boost"
			}
		},
		"rewards": [
			{
				"type": "puffish_skills:attribute",
				"data": {
					"attribute": "kubejs:treasure_distance",
					"value": -16,
					"operation": "addition"
				}
			}
		]
	},
	"treasure_distance_reduce_32": {
		"title": "kubejs.puffskill.def.treasure_distance_reduce_32.title",
		"description": "kubejs.puffskill.def.treasure_distance_reduce_32.desc",
		"extra_description": "kubejs.puffskill.exdesc.treasure_distance",
		"frame": {
			"type": "advancement",
			"data": {
				"frame": "goal"
			}
		},
		"icon": {
			"type": "effect",
			"data": {
				"effect": "health_boost"
			}
		},
		"rewards": [
			{
				"type": "puffish_skills:attribute",
				"data": {
					"attribute": "kubejs:treasure_distance",
					"value": -32,
					"operation": "addition"
				}
			}
		]
	},
	"treasure_distance_reduce_64": {
		"title": "kubejs.puffskill.def.treasure_distance_reduce_64.title",
		"description": "kubejs.puffskill.def.treasure_distance_reduce_64.desc",
		"extra_description": "kubejs.puffskill.exdesc.treasure_distance",
		"frame": {
			"type": "advancement",
			"data": {
				"frame": "challenge"
			}
		},
		"icon": {
			"type": "effect",
			"data": {
				"effect": "health_boost"
			}
		},
		"rewards": [
			{
				"type": "puffish_skills:attribute",
				"data": {
					"attribute": "kubejs:treasure_distance",
					"value": -64,
					"operation": "addition"
				}
			}
		]
	},
	"treasure_fortune_add_1": {
		"title": "kubejs.puffskill.def.treasure_fortune_add_1.title",
		"description": "kubejs.puffskill.def.treasure_fortune_add_1.desc",
		"extra_description": "kubejs.puffskill.exdesc.treasure_fortune",
		"frame": {
			"type": "advancement",
			"data": {
				"frame": "challenge"
			}
		},
		"icon": {
			"type": "effect",
			"data": {
				"effect": "health_boost"
			}
		},
		"rewards": [
			{
				"type": "puffish_skills:attribute",
				"data": {
					"attribute": "kubejs:treasure_fortune",
					"value": 1,
					"operation": "addition"
				}
			}
		]
	},
	"encode_ability_add_1": {
		"title": "kubejs.puffskill.def.encode_ability_add_1.title",
		"description": "kubejs.puffskill.def.encode_ability_add_1.desc",
		"extra_description": "kubejs.puffskill.exdesc.encode_ability",
		"frame": {
			"type": "advancement",
			"data": {
				"frame": "task"
			}
		},
		"icon": {
			"type": "effect",
			"data": {
				"effect": "health_boost"
			}
		},
		"rewards": [
			{
				"type": "puffish_skills:attribute",
				"data": {
					"attribute": "kubejs:encode_ability",
					"value": 1,
					"operation": "addition"
				}
			}
		]
	},
	"encode_ability_add_2": {
		"title": "kubejs.puffskill.def.encode_ability_add_2.title",
		"description": "kubejs.puffskill.def.encode_ability_add_2.desc",
		"extra_description": "kubejs.puffskill.exdesc.encode_ability",
		"frame": {
			"type": "advancement",
			"data": {
				"frame": "goal"
			}
		},
		"icon": {
			"type": "effect",
			"data": {
				"effect": "health_boost"
			}
		},
		"rewards": [
			{
				"type": "puffish_skills:attribute",
				"data": {
					"attribute": "kubejs:encode_ability",
					"value": 2,
					"operation": "addition"
				}
			}
		]
	},
	"encode_ability_add_3": {
		"title": "kubejs.puffskill.def.encode_ability_add_3.title",
		"description": "kubejs.puffskill.def.encode_ability_add_3.desc",
		"extra_description": "kubejs.puffskill.exdesc.encode_ability",
		"frame": {
			"type": "advancement",
			"data": {
				"frame": "challenge"
			}
		},
		"icon": {
			"type": "effect",
			"data": {
				"effect": "health_boost"
			}
		},
		"rewards": [
			{
				"type": "puffish_skills:attribute",
				"data": {
					"attribute": "kubejs:encode_ability",
					"value": 3,
					"operation": "addition"
				}
			}
		]
	},
	"overheal_add_01": {
		"title": "kubejs.puffskill.def.overheal_add_01.title",
		"description": "kubejs.puffskill.def.overheal_add_01.desc",
		"extra_description": "kubejs.puffskill.exdesc.overheal",
		"frame": {
			"type": "advancement",
			"data": {
				"frame": "challenge"
			}
		},
		"icon": {
			"type": "effect",
			"data": {
				"effect": "health_boost"
			}
		},
		"rewards": [
			{
				"type": "puffish_skills:attribute",
				"data": {
					"attribute": "attributeslib:overheal",
					"value": 0.1,
					"operation": "addition"
				}
			}
		]
	},
	"decode_ability_add_1": {
		"title": "kubejs.puffskill.def.decode_ability_add_1.title",
		"description": "kubejs.puffskill.def.decode_ability_add_1.desc",
		"extra_description": "kubejs.puffskill.exdesc.decode_ability",
		"frame": {
			"type": "advancement",
			"data": {
				"frame": "task"
			}
		},
		"icon": {
			"type": "effect",
			"data": {
				"effect": "health_boost"
			}
		},
		"rewards": [
			{
				"type": "puffish_skills:attribute",
				"data": {
					"attribute": "kubejs:decode_ability",
					"value": 1,
					"operation": "addition"
				}
			}
		]
	},
	"decode_ability_add_2": {
		"title": "kubejs.puffskill.def.decode_ability_add_2.title",
		"description": "kubejs.puffskill.def.decode_ability_add_2.desc",
		"extra_description": "kubejs.puffskill.exdesc.decode_ability",
		"frame": {
			"type": "advancement",
			"data": {
				"frame": "goal"
			}
		},
		"icon": {
			"type": "effect",
			"data": {
				"effect": "health_boost"
			}
		},
		"rewards": [
			{
				"type": "puffish_skills:attribute",
				"data": {
					"attribute": "kubejs:decode_ability",
					"value": 2,
					"operation": "addition"
				}
			}
		]
	},
	"decode_ability_add_3": {
		"title": "kubejs.puffskill.def.decode_ability_add_3.title",
		"description": "kubejs.puffskill.def.decode_ability_add_3.desc",
		"extra_description": "kubejs.puffskill.exdesc.decode_ability",
		"frame": {
			"type": "advancement",
			"data": {
				"frame": "challenge"
			}
		},
		"icon": {
			"type": "effect",
			"data": {
				"effect": "health_boost"
			}
		},
		"rewards": [
			{
				"type": "puffish_skills:attribute",
				"data": {
					"attribute": "kubejs:decode_ability",
					"value": 3,
					"operation": "addition"
				}
			}
		]
	},
	"life_steal_add_01": {
		"title": "kubejs.puffskill.def.life_steal_add_01.title",
		"description": "kubejs.puffskill.def.life_steal_add_01.desc",
		"extra_description": "kubejs.puffskill.exdesc.life_steal",
		"frame": {
			"type": "advancement",
			"data": {
				"frame": "challenge"
			}
		},
		"icon": {
			"type": "effect",
			"data": {
				"effect": "health_boost"
			}
		},
		"rewards": [
			{
				"type": "puffish_skills:attribute",
				"data": {
					"attribute": "attributeslib:life_steal",
					"value": 0.1,
					"operation": "addition"
				}
			}
		]
	}
}